tardyclock/__init__.py
tardyclock/cli.py
tardyclock/core.py
tardyclock-1.2.4.dist-info/METADATA
tardyclock-1.2.4.dist-info/WHEEL
tardyclock-1.2.4.dist-info/entry_points.txt
tardyclock-1.2.4.dist-info/RECORD
